agstream/__init__.py
agstream/__init__.py.bak
agstream/connector.py
agstream/connector.py.bak
agstream/decorators.py
agstream/devices.py
agstream/devices.py.bak
agstream/session.py
agstream/session.py.bak
agstream/session_extended.py
agstream/virtual_datasources.py
agstream/computing/__init__.py
agstream/computing/etp/__init__.py
agstream/computing/etp/etp_utils.py
agstream/computing/etp/etp_utils.py.bak
agstream/tests/__init__.py
agstream/tests/agstream_extended_session_test.py
agstream/tests/agstream_qualcorse.py
agstream/tests/agstream_test.py
agstream-2.0.12.dist-info/LICENSE
agstream-2.0.12.dist-info/METADATA
agstream-2.0.12.dist-info/WHEEL
agstream-2.0.12.dist-info/top_level.txt
agstream-2.0.12.dist-info/RECORD
