Metadata-Version: 2.1
Name: agstream
Version: 2.0.12
Summary: Agriscope python library to access data
Home-page: https://github.com/agriscope/agstream/
Author: Agriscope
Author-email: team@agriscope.fr
License: UNKNOWN
Platform: UNKNOWN
Classifier: Programming Language :: Python
Classifier: Development Status :: 1 - Planning
Classifier: License :: OSI Approved :: GNU Lesser General Public License v3 (LGPLv3)
Classifier: Natural Language :: French
Classifier: Operating System :: OS Independent
Classifier: Programming Language :: Python :: 2.7
Classifier: Topic :: Database :: Database Engines/Servers
License-File: LICENSE
Requires-Dist: pandas
Requires-Dist: future
